riemann/__init__.py
riemann/__main__.py
riemann/_summation.py
riemann/tests/__init__.py
riemann/tests/test_summation.py
riemann_sum-0.1.0.dist-info/LICENSE
riemann_sum-0.1.0.dist-info/METADATA
riemann_sum-0.1.0.dist-info/WHEEL
riemann_sum-0.1.0.dist-info/top_level.txt
riemann_sum-0.1.0.dist-info/RECORD
